odoo8_addon_website_mail_snippet_vertical_resize_base-8.0.1.0.0.99.dev6-py2.7-nspkg.pth
odoo8_addon_website_mail_snippet_vertical_resize_base-8.0.1.0.0.99.dev6.dist-info/DESCRIPTION.rst
odoo8_addon_website_mail_snippet_vertical_resize_base-8.0.1.0.0.99.dev6.dist-info/METADATA
odoo8_addon_website_mail_snippet_vertical_resize_base-8.0.1.0.0.99.dev6.dist-info/RECORD
odoo8_addon_website_mail_snippet_vertical_resize_base-8.0.1.0.0.99.dev6.dist-info/WHEEL
odoo8_addon_website_mail_snippet_vertical_resize_base-8.0.1.0.0.99.dev6.dist-info/metadata.json
odoo8_addon_website_mail_snippet_vertical_resize_base-8.0.1.0.0.99.dev6.dist-info/namespace_packages.txt
odoo8_addon_website_mail_snippet_vertical_resize_base-8.0.1.0.0.99.dev6.dist-info/top_level.txt
odoo_addons/website_mail_snippet_vertical_resize_base/README.rst
odoo_addons/website_mail_snippet_vertical_resize_base/__init__.py
odoo_addons/website_mail_snippet_vertical_resize_base/__openerp__.py
odoo_addons/website_mail_snippet_vertical_resize_base/i18n/de.po
odoo_addons/website_mail_snippet_vertical_resize_base/i18n/es.po
odoo_addons/website_mail_snippet_vertical_resize_base/i18n/fr.po
odoo_addons/website_mail_snippet_vertical_resize_base/i18n/sl.po
odoo_addons/website_mail_snippet_vertical_resize_base/i18n/website_mail_snippet_vertical_resize_base.pot
odoo_addons/website_mail_snippet_vertical_resize_base/static/description/icon.png
odoo_addons/website_mail_snippet_vertical_resize_base/static/description/icon.svg
odoo_addons/website_mail_snippet_vertical_resize_base/static/src/js/vertical_resize.js
odoo_addons/website_mail_snippet_vertical_resize_base/views/assets.xml
odoo_addons/website_mail_snippet_vertical_resize_base/views/snippets.xml
